{
  "1001": {
    "description": "Temporal Configuration Error",
    "message": "An internal error occurred.",
    "retriable": false,
    "http_code": 500
  },
  "1002": {
    "description": "One or more input parameters are invalid",
    "message": "Bad Request",
    "retriable": false,
    "http_code": 400
  },
  "1003": {
    "description": "Requested Resource is not found",
    "message": "Resource not found",
    "retriable": false,
    "http_code": 404
  },
  "1004": {
    "description": "Could not read from the file",
    "message": "An internal error occurred.",
    "retriable": false,
    "http_code": 500
  },
  "1005": {
    "description": "Could not write to the file",
    "message": "An internal error occurred.",
    "retriable": false,
    "http_code": 500
  },
  "1006": {
    "description": "JSON Parsing Error",
    "message": "An internal error occurred.",
    "retriable": false,
    "http_code": 500
  },
  "1007": {
    "description": "Maximum retries exceeded",
    "message": "An internal error occurred.",
    "retriable": false,
    "http_code": 500
  },
  "1008": {
    "description": "Time Limit Exceeded",
    "message": "An internal error occurred.",
    "retriable": false,
    "http_code": 500
  },
  "1009": {
    "description": "Input validation error",
    "message": "Invalid input parameters provided",
    "retriable": false,
    "http_code": 400
  },
  "1010": {
    "description": "Resource state conflict error",
    "message": "Resource is in an invalid state for the requested operation",
    "retriable": false,
    "http_code": 409
  },
  "1011": {
    "description": "Internal Server Error",
    "message": "An internal error occurred.",
    "retriable": false,
    "http_code": 500
  },
  "1012": {
    "description": "Model validation and conversion error",
    "message": "An internal error occurred.",
    "retriable": false,
    "http_code": 500
  },
  "1013": {
    "description": "Base64 Encoding Error",
    "message": "An internal error occurred.",
    "retriable": false,
    "http_code": 500
  },
  "1014": {
    "description": "Base64 Decoding Error",
    "message": "An internal error occurred.",
    "retriable": false,
    "http_code": 500
  },
  "1015": {
    "description": "Empty or Nil resource Error",
    "message": "An internal error occurred.",
    "retriable": false,
    "http_code": 500
  },
  "1016": {
    "description": "CSR Generation Failed",
    "message": "An internal error occurred.",
    "retriable": false,
    "http_code": 500
  },
  "1017": {
    "description": "Could not launch Temporal Workflow from the Orchestrator Layer",
    "message": "An internal error occurred.",
    "retriable": false,
    "http_code": 500
  },
  "2001": {
    "description": "Database Connection Closed",
    "message": "An internal error occurred.",
    "retriable": false,
    "http_code": 500
  },
  "2002": {
    "description": "Could not begin/commit/rollback the database transaction",
    "message": "An internal error occurred.",
    "retriable": true,
    "http_code": 500
  },
  "2003": {
    "description": "Error when inserting data into the database",
    "message": "An internal error occurred.",
    "retriable": false,
    "http_code": 500
  },
  "2004": {
    "description": "Error while reading the data from the database",
    "message": "An internal error occurred.",
    "retriable": false,
    "http_code": 500
  },
  "2005": {
    "description": "Error when deleting record(s) in the database",
    "message": "An internal error occurred.",
    "retriable": false,
    "http_code": 500
  },
  "2006": {
    "description": "Error when fetching data from the database",
    "message": "An internal error occurred.",
    "retriable": false,
    "http_code": 500
  },
  "2007": {
    "description": "Requested Resource is not found in the database",
    "message": "Resource not found",
    "retriable": false,
    "http_code": 404
  },
  "2100": {
    "description": "Volume not found in the database",
    "message": "Volume not found",
    "retriable": false,
    "http_code": 404
  },
  "2101": {
    "description": "Account not found in the database",
    "message": "Account not found",
    "retriable": false,
    "http_code": 404
  },
  "2102": {
    "description": "Pool not found in the database",
    "message": "Pool not found",
    "retriable": false,
    "http_code": 404
  },
  "3001": {
    "description": "GCP Client Initialization Error",
    "message": "An internal error occurred.",
    "retriable": false,
    "http_code": 500
  },
  "3002": {
    "description": "Private Service Access (PSA) is not configured",
    "message": "Setup/Configure Private Service Access (PSA) Peering",
    "retriable": false,
    "http_code": 400
  },
  "3003": {
    "description": "GCP Resource Provisioning Error",
    "message": "An internal error occurred.",
    "retriable": true,
    "http_code": 500
  },
  "3004": {
    "description": "Could not fetch the required GCP resource(s)",
    "message": "An internal error occurred.",
    "retriable": true,
    "http_code": 500
  },
  "3005": {
    "description": "GCP Resource De-provisioning Error",
    "message": "An internal error occurred.",
    "retriable": true,
    "http_code": 500
  },
  "3007": {
    "description": "GCP Service Account Deletion Error",
    "message": "An internal error occurred.",
    "retriable": true,
    "http_code": 500
  },
  "3006": {
    "description": "GCP Resource Already Exists Error",
    "message": "The requested resource already exists",
    "retriable": false,
    "http_code": 409
  },
  "3008": {
    "description": "GCP Service Account Deletion Non-Retriable Error",
    "message": "An internal error occurred.",
    "retriable": false,
    "http_code": 500
  },
  "3009": {
    "description": "Customer's data subnet exhausted",
    "message": "Couldn't find free blocks in allocated IP ranges. Please allocate new ranges for this service provider",
    "retriable": false,
    "http_code": 400
  },
  "4001": {
    "description": "VSA Cluster Provisioning Error",
    "message": "An internal error occurred.",
    "retriable": true,
    "http_code": 500
  },
  "4002": {
    "description": "Error fetching VSA Cluster Details",
    "message": "An internal error occurred.",
    "retriable": true,
    "http_code": 500
  },
  "4003": {
    "description": "VSA Cluster De-provisioning Error",
    "message": "An internal error occurred.",
    "retriable": true,
    "http_code": 500
  },
  "4004": {
    "description": "Invalid VSA Cluster State",
    "message": "An internal error occurred.",
    "retriable": false,
    "http_code": 500
  },
  "4005": {
    "description": "VSA Cluster - Node Not Found",
    "message": "An internal error occurred.",
    "retriable": false,
    "http_code": 500
  },
  "4006": {
    "description": "VSA Cluster Node IP Address Not Found",
    "message": "VSA cluster node IP address not found",
    "retriable": false,
    "http_code": 500
  },
  "4007": {
    "description": "VSA Cluster Update Error",
    "message": "Failed to update VSA cluster",
    "retriable": true,
    "http_code": 500
  },
  "4008": {
    "description": "VLM Client Initialization Error",
    "message": "Failed to initialize VLM client",
    "retriable": false,
    "http_code": 500
  },
  "4011": {
    "description": "No node found for the pool",
    "message": "An internal error occurred.",
    "retriable": false,
    "http_code": 500
  },
  "4009": {
    "description": "Pool creation error",
    "message": "All host groups could not be found.",
    "retriable": false,
    "http_code": 400
  },
  "4010": {
    "description": "Cluster deletion error",
    "message": "An internal error occurred.",
    "retriable": false,
    "http_code": 500
  },
  "4012": {
    "description": "Workflow task queue is empty or invalid",
    "message": "An internal error occurred.",
    "retriable": false,
    "http_code": 500
  },
  "5001": {
    "description": "Error fetching ONTAP version",
    "message": "An internal error occurred.",
    "retriable": true,
    "http_code": 500
  },
  "5002": {
    "description": "Error when creating VSA SVM",
    "message": "An internal error occurred.",
    "retriable": true,
    "http_code": 500
  },
  "5003": {
    "description": "Error when deleting VSA SVM",
    "message": "An internal error occurred.",
    "retriable": true,
    "http_code": 500
  },
  "5004": {
    "description": "VSA Cluster - SVM Not Found",
    "message": "An internal error occurred.",
    "retriable": false,
    "http_code": 500
  },
  "5006": {
    "description": "Ontap Rest Error",
    "message": "An internal error occurred.",
    "retriable": false,
    "http_code": 500
  },
  "5007": {
    "description": "ONTAP Inconsistent Resource Error",
    "message": "ONTAP resource is in an inconsistent state",
    "retriable": false,
    "http_code": 500
  },
  "5008": {
    "description": "Failed to create ONTAP Rest Client",
    "message": "An internal error occurred.",
    "retriable": false,
    "http_code": 500
  },
  "5009": {
    "description": "Constituent Volumes Limit Exceeded",
    "message": "Constituent Volumes Limit Exceeded.",
    "retriable": false,
    "http_code": 400
  },
  "5010": {
    "description": "Volume Exceeds Maximum Size",
    "message": "The volume size exceeds the maximum allowed size for this storage pool.",
    "retriable": false,
    "http_code": 400
  },
  "5011": {
    "description": "Invalid Constituent Volume Count",
    "message": "The constituent volume count must be greater than zero.",
    "retriable": false,
    "http_code": 400
  },
  "5012": {
    "description": "No Aggregates With Available Capacity",
    "message": "All storage aggregates have reached their maximum capacity and cannot accommodate additional volumes.",
    "retriable": false,
    "http_code": 400
  },
  "5013": {
    "description": "Insufficient Aggregate Capacity",
    "message": "Insufficient storage capacity available across aggregates to fulfill the volume creation request.",
    "retriable": false,
    "http_code": 400
  },
  "5014": {
    "description": "ONTAP Aggregate Count Mismatch",
    "message": "Some aggregates may be unavailable/offline to fulfil this request.",
    "retriable": false,
    "http_code": 500
  },
  "5015": {
    "description": "Aggregate is offline",
    "message": "Storage aggregate is not in online state and cannot accommodate volumes.",
    "retriable": false,
    "http_code": 500
  },
  "6020": {
    "description": "IAM client Not Found",
    "message": "IAM client Not Found",
    "retriable": false,
    "http_code": 500
  },
  "6021": {
    "description": "Failed to parse projectNumber",
    "message": "Failed to parse projectNumber",
    "retriable": false,
    "http_code": 500
  },
  "6022": {
    "description": "Failed to marshal jwt payload",
    "message": "Failed to marshal jwt payload",
    "retriable": false,
    "http_code": 500
  },
  "6023": {
    "description": "Failed to marshal JSON",
    "message": "Failed to marshal JSON",
    "retriable": false,
    "http_code": 500
  },
  "6024": {
    "description": "Failed to create HTTP request",
    "message": "Failed to create HTTP request",
    "retriable": false,
    "http_code": 500
  },
  "6025": {
    "description": "Failed to execute HTTP request",
    "message": "Failed to execute HTTP request",
    "retriable": false,
    "http_code": 500
  },
  "6026": {
    "description": "Failed to read response body",
    "message": "Failed to read response body",
    "retriable": false,
    "http_code": 500
  },
  "6027": {
    "description": "Failed to unmarshal CCFE response",
    "message": "Failed to unmarshal CCFE response",
    "retriable": false,
    "http_code": 500
  },
  "6028": {
    "description": "Failed to read quota value from CCFE response",
    "message": "Failed to read quota value from CCFE response",
    "retriable": false,
    "http_code": 500
  },
  "6029": {
    "description": "Failed to create NewIamCred",
    "message": "Failed to create NewIamCred",
    "retriable": false,
    "http_code": 500
  },
  "6030": {
    "description": "Failed To Generate Access Token",
    "message": "Failed To Generate Access Token",
    "retriable": false,
    "http_code": 500
  },
  "6057": {
    "description": "Error describing SDE Operation",
    "message": "Error describing SDE Operation",
    "retriable": false,
    "http_code": 500
  },
  "6058": {
    "description": "Error SDE job not done",
    "message": "Error SDE job not done",
    "retriable": false,
    "http_code": 500
  },
  "6059": {
    "description": "Delete Kms Job Failed",
    "message": "Error while deleting KMS configuration",
    "retriable": false,
    "http_code": 500
  },
  "6060": {
    "description": "Client Error during StartProjectEvent",
    "message": "Client Error during StartProjectEvent",
    "retriable": false,
    "http_code": 500
  },
  "6061": {
    "description": "Invalid Operation Name",
    "message": "Invalid Operation Name",
    "retriable": false,
    "http_code": 500
  },
  "6063": {
    "description": "Cmek Migration failure",
    "message": "Error while migrating KMS configuration",
    "retriable": false,
    "http_code": 500
  },
  "6066": {
    "description": "Cmek Deletion failure",
    "message": "Error while deleting KMS configuration",
    "retriable": false,
    "http_code": 500
  },
  "6067": {
    "description": "Cmek Update failure",
    "message": "Error while updating KMS configuration",
    "retriable": false,
    "http_code": 500
  },
  "6068": {
    "description": "Cmek Creation failure",
    "message": "Error while creating KMS configuration",
    "retriable": false,
    "http_code": 500
  },
  "6069": {
    "description": "Cluster serial number generation failed",
    "message": "Error while generating Cluster serial number",
    "retriable": false,
    "http_code": 500
  },
  "6073": {
    "description": "Client error during HandleResourceEvent",
    "message": "Client error during HandleResourceEvent",
    "retriable": false,
    "http_code": 500
  },
  "6074": {
    "description": "FinishProjectEvent failure",
    "message": "Client Error during FinishProjectEvent",
    "retriable": true,
    "http_code": 500
  },
  "6075": {
    "description": "HandleResourceEvent failure",
    "message": "Cannot delete resource while it is transitioning",
    "retriable": true,
    "http_code": 500
  },
  "6076": {
    "description": "Resource not found",
    "message": "Resource not found",
    "retriable": false,
    "http_code": 404
  },
  "6077": {
    "description": "Bad request error",
    "message": "Bad request error",
    "retriable": false,
    "http_code": 400
  },
  "6078": {
    "description": "Internal server error",
    "message": "Internal server error",
    "retriable": false,
    "http_code": 500
  },
  "6079": {
    "description": "Unauthorised error",
    "message": "Unauthorised error",
    "retriable": false,
    "http_code": 401
  },
  "6080": {
      "description": "Forbidden error",
      "message": "Forbidden error",
      "retriable": false,
      "http_code": 403
  },
  "6081": {
      "description": "Conflict error",
      "message": "Conflict error",
      "retriable": false,
      "http_code": 409
  },
  "6082": {
      "description": "Not implemented yet error",
      "message": "Not implemented yet error",
      "retriable": true,
      "http_code": 501
  },
  "6083": {
    "description": "Too many requests error",
    "message": "Too many requests error",
    "retriable": true,
    "http_code": 429
  },
  "6084": {
    "description": "FinishProjectEvent error while listing resources",
    "message": "Error occurred while listing resources during FinishProjectEvent",
    "retriable": false,
    "http_code": 500
  },
  "6085": {
    "description": "FinishProjectEvent error while deleting resources",
    "message": "Error occurred while deleting resources during FinishProjectEvent",
    "retriable": false,
    "http_code": 400
  },
  "6086": {
    "description": "FinishProjectEvent hard delete resources error",
    "message": "Error occurred during hard delete of resources in FinishProjectEvent",
    "retriable": false,
    "http_code": 400
  },
  "7001": {
    "description": "Snapshot Deletion Error",
    "message": "Cannot delete snapshot while snapshot is in use",
    "retriable": false,
    "http_code": 400
  },
  "7002": {
    "description": "Snapshot Deletion Error",
    "message": "Cannot delete snapshot because volume is not online",
    "retriable": false,
    "http_code": 400
  },
  "7003": {
    "description": "Snapshot Policy Validation Error",
    "message": "At least one snapshot policy schedule is required",
    "retriable": false,
    "http_code": 400
  },
  "7004": {
    "description": "SnapshotPolicy Creation Error",
    "message": "Cannot create too many snapshot policies",
    "retriable": false,
    "http_code": 400
  },
  "7005": {
    "description": "Volume Deletion Error",
    "message": "Cannot delete volume while volume is in use",
    "retriable": false,
    "http_code": 400
  },
  "9001": {
    "description": "VLM Regional Quota Exceeded",
    "message": "Resource quota exceeded in the specified region. Please contact support to increase the quota limit or try a different region.",
    "retriable": false,
    "http_code": 507
  },
  "9002": {
    "description": "VLM Zonal Quota Exceeded",
    "message": "Resource quota exceeded in the specified zone. Please contact support to increase the quota limit or try a different zone.",
    "retriable": false,
    "http_code": 507
  },
  "9003": {
    "description": "VLM General Quota Exceeded",
    "message": "Resource quota exceeded. Please contact support to increase the quota limit.",
    "retriable": false,
    "http_code": 507
  },
  "9004": {
    "description": "VLM Resource Not Available in Zone",
    "message": "The requested resource is not available in the specified zone. Please try a different zone or resource type.",
    "retriable": false,
    "http_code": 500
  },
  "9005": {
    "description": "VLM Zone Resource Pool Exhausted",
    "message": "The zone's resource pool is currently exhausted. Please try a different zone or try again later.",
    "retriable": true,
    "http_code": 507
  },
  "9006": {
    "description": "VLM Zone Resource Pool Exhausted with Details",
    "message": "The zone's resource pool is currently exhausted with specific constraints. Please try a different zone or resource configuration.",
    "retriable": true,
    "http_code": 507
  },
  "9007": {
    "description": "VLM Insufficient Resources in Zone",
    "message": "Insufficient resources available in the specified zone to fulfill the request. Please try a different zone or try again later.",
    "retriable": true,
    "http_code": 507
  },
  "9008": {
    "description": "VLM VM Type Unavailable in Zone",
    "message": "The requested VM type is currently unavailable in the specified zone. Please try a different zone or VM configuration.",
    "retriable": true,
    "http_code": 507
  },
  "9009": {
    "description": "VLM VM Type Unavailable with Reason",
    "message": "The requested VM type is currently unavailable in the specified zone due to specific constraints. Please try the suggested alternatives.",
    "retriable": true,
    "http_code": 507
  },
  "9010": {
    "description": "VLM Rate Limit Exceeded",
    "message": "Operation rate limit exceeded. Please wait before retrying the operation.",
    "retriable": true,
    "http_code": 429
  },
  "9011": {
    "description": "VLM Disk Rate Limited",
    "message": "Disk operation rate limited. Please wait before retrying the disk operation.",
    "retriable": true,
    "http_code": 429
  },
  "9012": {
    "description": "VLM Resource Not Ready",
    "message": "The requested resource is not ready for the operation. Please wait and try again.",
    "retriable": true,
    "http_code": 503
  },
  "9013": {
    "description": "VLM Insufficient Permissions",
    "message": "Insufficient permissions to perform the requested operation. Please contact support.",
    "retriable": false,
    "http_code": 500
  },
  "9014": {
    "description": "VLM Project Constraint Violated",
    "message": "Project constraint violated. The operation is not allowed for this project.",
    "retriable": false,
    "http_code": 500
  },
  "9015": {
    "description": "VLM CPU Platform Mismatch",
    "message": "CPU platform mismatch. The selected machine type requires a specific CPU platform that does not match the specified configuration.",
    "retriable": false,
    "http_code": 500
  },
  "9016": {
    "description": "VLM Service Account Access Denied",
    "message": "Service account access denied. The service account does not have the required permissions.",
    "retriable": false,
    "http_code": 500
  },
  "9017": {
    "description": "VLM Invalid Machine Image Update",
    "message": "Invalid machine image update. Updating the source machine image is not supported.",
    "retriable": false,
    "http_code": 500
  },
  "9018": {
    "description": "VLM Workflow Error",
    "message": "An error occurred during VLM workflow execution. Please try again or contact support if the issue persists.",
    "retriable": true,
    "http_code": 500
  },
  "9019": {
    "description": "VLM Cloud VM offline",
    "message": "Cloud VM is offline. Please check the resource status and try again.",
    "retriable": false,
    "http_code": 503
  },
  "9020": {
    "description": "VLM Config Parse Error",
    "message": "An error occurred during VLM config parsing. Please contact support.",
    "retriable": false,
    "http_code": 500
  },
  "7006": {
    "description": "VolumeRevert failure",
    "message": "Error reverting volume - Cannot revert a Volume Replication Destination Volume",
    "retriable": true,
    "http_code": 409
  },
  "7007": {
    "description": "LunUpdate Failure",
    "message": "Error updating volume - Cannot update the volume with the specified size. Please increase the volume size.",
    "retriable": false,
    "http_code": 400
  },
  "7008": {
    "description": "VolumeRestore Failure",
    "message": "Error restoring volume - Cannot restore the Volume with the specified size. Please increase the volume size",
    "retriable": false,
    "http_code": 400
  },
  "7009": {
    "description": "VolumeRevert Failure",
    "message": "Error reverting volume - Cannot revert the volume as snapshot is in use by the cloned volume",
    "retriable": false,
    "http_code": 400
  },
  "7010": {
    "description": "SnapshotCreate Failure",
    "message": "Error creating snapshot - snapshot already exists as part of volume clone",
    "retriable": false,
    "http_code": 409
  },
  "7011": {
    "description": "CloneVolumeCreate Failure",
    "message": "Error creating volume - Maximum limit for nested clone volumes has been reached",
    "retriable": false,
    "http_code": 400
  },
  "6100": {
    "description": "Replication Schedule Unspecified",
    "message": "Replication schedule must be specified",
    "retriable": false,
    "http_code": 400
  },
  "6101": {
    "description": "Labels Marshal Failure Error",
    "message": "Failed to marshal labels",
    "retriable": false,
    "http_code": 500
  },
  "6102": {
    "description": "Labels Count Exceeded Error",
    "message": "Label count exceeds the maximum limit of 64",
    "retriable": false,
    "http_code": 400
  },
  "6103": {
    "description": "Labels Key Required Error",
    "message": "Label key is required",
    "retriable": false,
    "http_code": 400
  },
  "6104": {
    "description": "Labels Key Too Long Characters Error",
    "message": "Label key exceeds the maximum length of 63 characters",
    "retriable": false,
    "http_code": 400
  },
  "6105": {
    "description": "Labels Key Too Long Bytes Error",
    "message": "Label key exceeds the maximum encoded length of 128 bytes",
    "retriable": false,
    "http_code": 400
  },
  "6106": {
    "description": "Labels Value Too Long Characters Error",
    "message": "Label value exceeds the maximum length of 63 characters",
    "retriable": false,
    "http_code": 400
  },
  "6107": {
    "description": "Labels Value Too Long Bytes Error",
    "message": "Label value exceeds the maximum encoded length of 128 bytes",
    "retriable": false,
    "http_code": 400
  },
  "6108": {
    "description": "Get Signed Token Error",
    "message": "Failed to get signed token",
    "retriable": false,
    "http_code": 500
  },
  "6109": {
    "description": "Parse Source Location Error",
    "message": "Failed to parse source location",
    "retriable": false,
    "http_code": 500
  },
  "6110": {
    "description": "Parse Destination Location Error",
    "message": "Failed to parse destination location",
    "retriable": false,
    "http_code": 400
  },
  "6111": {
    "description": "Get Source Base Path Error",
    "message": "Failed to get source base path",
    "retriable": false,
    "http_code": 500
  },
  "6112": {
    "description": "Get Destination Base Path Error",
    "message": "Failed to get destination base path",
    "retriable": false,
    "http_code": 500
  },
  "6113": {
    "description": "Validate Create Resource ID In Use Error",
    "message": "Resource ID is already in use",
    "retriable": false,
    "http_code": 409
  },
  "6114": {
    "description": "List Volumes Error",
    "message": "Failed to list volumes",
    "retriable": false,
    "http_code": 500
  },
  "6115": {
    "description": "List Pools Error",
    "message": "Failed to list pools",
    "retriable": false,
    "http_code": 500
  },
  "6116": {
    "description": "Get Pool Not Found Error",
    "message": "Destination pool not found",
    "retriable": false,
    "http_code": 404
  },
  "6117": {
    "description": "Internal Describe Pool API Error",
    "message": "Failed to describe pool",
    "retriable": false,
    "http_code": 500
  },
  "6118": {
    "description": "Internal Describe Pool Not Found Error",
    "message": "Internal pool not found",
    "retriable": false,
    "http_code": 500
  },
  "6119": {
    "description": "Internal Accept Cluster Peer API Error",
    "message": "Failed to accept cluster peer",
    "retriable": false,
    "http_code": 500
  },
  "6120": {
    "description": "Internal Accept Cluster Peer Not Found Error",
    "message": "Internal cluster peer not found",
    "retriable": false,
    "http_code": 500
  },
  "6121": {
    "description": "Describing Job Not Found Error",
    "message": "Job not found",
    "retriable": false,
    "http_code": 404
  },
  "6122": {
    "description": "Describing Job API Error",
    "message": "Failed to describe job",
    "retriable": false,
    "http_code": 500
  },
  "6123": {
    "description": "Job Not Finished Error",
    "message": "Job not finished",
    "retriable": false,
    "http_code": 400
  },
  "6124": {
    "description": "Creating Destination Volume Error",
    "message": "Failed to create destination volume",
    "retriable": false,
    "http_code": 500
  },
  "6125": {
    "description": "Accept SVM Peer Error",
    "message": "Failed to accept SVM peer",
    "retriable": false,
    "http_code": 500
  },
  "6126": {
    "description": "Failed To Marshal Model Error",
    "message": "Failed to marshal model",
    "retriable": false,
    "http_code": 500
  },
  "6127": {
    "description": "Failed To Unmarshal Error",
    "message": "Failed to unmarshal data",
    "retriable": false,
    "http_code": 500
  },
  "6128": {
    "description": "Validate Create Source Volume Is Flex Cache Volume Error",
    "message": "Source cannot be a FlexCache volume",
    "retriable": false,
    "http_code": 400
  },
  "6129": {
    "description": "Validate Create Source Volume In Replication Group Error",
    "message": "Source volume is already in a replication",
    "retriable": false,
    "http_code": 400
  },
  "6130": {
    "description": "Validate Create Source Volume Not Ready Error",
    "message": "Source volume is not ready",
    "retriable": false,
    "http_code": 400
  },
  "6131": {
    "description": "Validate Storage Pool URI Error",
    "message": "Invalid storage pool URI",
    "retriable": false,
    "http_code": 400
  },
  "6132": {
    "description": "Validate Destination Pool Transitioning Error",
    "message": "Destination pool is transitioning",
    "retriable": false,
    "http_code": 400
  },
  "6133": {
    "description": "Validate Destination Storage Pool State Error",
    "message": "Destination pool is in unhealthy state, Please try after some time",
    "retriable": false,
    "http_code": 400
  },
  "6134": {
    "description": "Destination Pool Size Error",
    "message": "Destination pool size is insufficient",
    "retriable": false,
    "http_code": 400
  },
  "6135": {
    "description": "Get Signed Callback Token Error",
    "message": "Failed to get signed callback token",
    "retriable": false,
    "http_code": 500
  },
  "6136": {
    "description": "Get Replication Quota Limit Internal Error",
    "message": "Failed to get replication quota limit",
    "retriable": false,
    "http_code": 500
  },
  "6137": {
    "description": "Describe Source Pool Error",
    "message": "Failed to describe source pool",
    "retriable": false,
    "http_code": 500
  },
  "6138": {
    "description": "Hydrate Volume Create Error",
    "message": "Failed to hydrate volume creation",
    "retriable": false,
    "http_code": 500
  },
  "6139": {
    "description": "Getting SVM Peer Error",
    "message": "Failed to get SVM peer",
    "retriable": false,
    "http_code": 500
  },
  "6140": {
    "description": "Failed To Get Snapmirror Details From ONTAP Get Multiple Error",
    "message": "Failed to get snapmirror details from ONTAP for get multiple operations",
    "retriable": false,
    "http_code": 500
  },
  "6141": {
    "description": "Failed To Get Snapmirror Details From ONTAP Mount Job Error",
    "message": "Failed to get snapmirror details from ONTAP for mount job",
    "retriable": false,
    "http_code": 500
  },
  "6142": {
    "description": "Region Zone Parsing Error Current Region",
    "message": "Failed to parse current region",
    "retriable": false,
    "http_code": 500
  },
  "6143": {
    "description": "Region Zone Parsing Error Destination Region",
    "message": "Failed to parse destination region",
    "retriable": false,
    "http_code": 500
  },
  "6144": {
    "description": "Region Zone Parsing Error Source Region",
    "message": "Failed to parse source region",
    "retriable": false,
    "http_code": 500
  },
  "6145": {
    "description": "Region Zone Parsing Error Paired Region URI",
    "message": "Failed to get paired region URI",
    "retriable": false,
    "http_code": 500
  },
  "6146": {
    "description": "Project Parsing Error",
    "message": "Failed to parse project",
    "retriable": false,
    "http_code": 500
  },
  "6147": {
    "description": "Google Proxy Internal Get Multiple Replications Error",
    "message": "Failed to get multiple replications",
    "retriable": false,
    "http_code": 500
  },
  "6148": {
    "description": "Google Proxy Internal Get Multiple Replications Bad Request Error",
    "message": "Bad request getting multiple replications",
    "retriable": false,
    "http_code": 400
  },
  "6149": {
    "description": "Google Proxy Internal Get Multiple Replications Not Found Error",
    "message": "Internal server error getting multiple replications",
    "retriable": false,
    "http_code": 404
  },
  "6150": {
    "description": "Google Proxy Internal Get Multiple Replications Internal Server Error",
    "message": "Internal server error getting multiple replications",
    "retriable": false,
    "http_code": 500
  },
  "6151": {
    "description": "Google Proxy Internal Get Multiple Replications Unauthorized Error",
    "message": "Unauthorized to get multiple replications",
    "retriable": false,
    "http_code": 500
  },
  "6152": {
    "description": "Google Proxy Internal Get Multiple Replications Forbidden Error",
    "message": "Forbidden to get multiple replications",
    "retriable": false,
    "http_code": 500
  },
  "6153": {
    "description": "Google Proxy Internal Get Multiple Replications Unknown Error",
    "message": "Unknown error getting multiple replications",
    "retriable": false,
    "http_code": 500
  },
  "6154": {
    "description": "Get Remote Replication Jobs Error",
    "message": "Failed to get remote replication jobs",
    "retriable": false,
    "http_code": 500
  },
  "6155": {
    "description": "Get Local Replication Jobs Error",
    "message": "Failed to get local replication jobs",
    "retriable": false,
    "http_code": 500
  },
  "6156": {
    "description": "Replication Job Already In Process Error",
    "message": "Another replication job is already in progress for this resource",
    "retriable": false,
    "http_code": 409
  },
  "6157": {
    "description": "Mounting Volume Replication Error",
    "message": "Failed to mount volume replication",
    "retriable": false,
    "http_code": 500
  },
  "6158": {
    "description": "Dehydrate Snapshots Error",
    "message": "Failed to dehydrate snapshots",
    "retriable": false,
    "http_code": 500
  },
  "6160": {
    "description": "Dehydrate Volume Error",
    "message": "Failed to dehydrate volume",
    "retriable": false,
    "http_code": 500
  },
  "6161": {
    "description": "Dehydrate Volume Replication Error",
    "message": "Failed to dehydrate volume replication",
    "retriable": false,
    "http_code": 500
  },
  "6163": {
    "description": "Empty Update Replication Payload Error",
    "message": "Update replication payload is empty",
    "retriable": false,
    "http_code": 400
  },
  "6164": {
    "description": "Replication Schedule Unspecified Error",
    "message": "Replication schedule must be specified",
    "retriable": false,
    "http_code": 400
  },
  "6165": {
    "description": "Describe Volume Error",
    "message": "Failed to describe volume",
    "retriable": false,
    "http_code": 500
  },
  "6166": {
    "description": "Replication Quota Limit Exceeded Error",
    "message": "Replication quota limit exceeded",
    "retriable": false,
    "http_code": 400
  },
  "6167": {
    "description": "Get Volume Quota Limit Internal Error",
    "message": "Failed to get volume quota limit",
    "retriable": false,
    "http_code": 500
  },
  "6168": {
    "description": "Validate Create Replication CVP Internal Get Volume Count Error",
    "message": "Failed to get volume count for replication validation",
    "retriable": false,
    "http_code": 500
  },
  "6169": {
    "description": "Volume Quota Limit Exceeded Error",
    "message": "Volume quota limit exceeded",
    "retriable": false,
    "http_code": 400
  },
  "6170": {
    "description": "Validate Get Volume Replication Creation Error",
    "message": "Failed to validate volume during replication creation",
    "retriable": false,
    "http_code": 500
  },
  "6171": {
    "description": "Validate Get Volume Replication Creation Volume Not Found Error",
    "message": "Volume not found",
    "retriable": false,
    "http_code": 404
  },
  "6172": {
    "description": "Get Volume Create Token In Use Remote Share Name Error",
    "message": "Remote share name already exists",
    "retriable": false,
    "http_code": 409
  },
  "6173": {
    "description": "Get Volume Create Token In Use Remote Resource ID Error",
    "message": "Remote resource ID already exists",
    "retriable": false,
    "http_code": 409
  },
  "6174": {
    "description": "Validate Create Replication Error",
    "message": "Failed to validate create replication",
    "retriable": false,
    "http_code": 500
  },
  "6175": {
    "description": "Service Level Mismatch Error",
    "message": "Service level mismatch",
    "retriable": false,
    "http_code": 400
  },
  "6176": {
    "description": "ONTAP Cluster Not Found Error",
    "message": "ONTAP cluster not found",
    "retriable": false,
    "http_code": 500
  },
  "6177": {
    "description": "Validate Create Replication CVP Internal Get Replication Count Error",
    "message": "Failed to get replication count",
    "retriable": false,
    "http_code": 500
  },
  "6178": {
    "description": "Google Proxy Internal Get Multiple Replications Get Active Replication Jobs Bad Request Error",
    "message": "Bad request getting active replication jobs",
    "retriable": false,
    "http_code": 500
  },
  "6179": {
    "description": "Google Proxy Internal Get Multiple Replications Get Active Replication Jobs Internal Server Error",
    "message": "Internal server error getting active replication jobs",
    "retriable": false,
    "http_code": 500
  },
  "6180": {
    "description": "Google Proxy Internal Get Multiple Replications Get Active Replication Jobs Unauthorized Error",
    "message": "Unauthorized to get active replication jobs",
    "retriable": false,
    "http_code": 500
  },
  "6181": {
    "description": "Google Proxy Internal Get Multiple Replications Get Active Replication Jobs Forbidden Error",
    "message": "Forbidden to get active replication jobs",
    "retriable": false,
    "http_code": 500
  },
  "6182": {
    "description": "Google Proxy Internal Get Multiple Replications Get Active Replication Jobs Not Found Error",
    "message": "Active replication jobs not found",
    "retriable": false,
    "http_code": 500
  },
  "6183": {
    "description": "Google Proxy Internal Get Multiple Replications Get Active Replication Jobs Unknown Error",
    "message": "Unknown error getting active replication jobs",
    "retriable": false,
    "http_code": 500
  },
  "6184": {
    "description": "Internal job failed",
    "message": "Internal job failed",
    "retriable": false,
    "http_code": 500
  },
  "6185": {
    "description": "Google Proxy Internal Resume Replication",
    "message": "Failed to resume replication",
    "retriable": false,
    "http_code": 500
  },
  "6186": {
    "description": "Resume Replication Volume State Offline",
    "message": "Failed to resume replication as volume is offline",
    "retriable": false,
    "http_code": 500
  },
  "6187": {
    "description": "Destination Volume Used Size Greater Than Source Volume Available Quota",
    "message": "Failed to resume replication as destination volume used size is greater than source volume available quota",
    "retriable": false,
    "http_code": 400
  },
  "6188": {
    "description": "Failed To Get Lun Details From ONTAP",
    "message": "Failed to get lun details from ONTAP",
    "retriable": false,
    "http_code": 500
  },
  "6189": {
    "description": "Google Proxy Internal Stop Replication",
    "message": "Failed to stop replication",
    "retriable": false,
    "http_code": 500
  },
  "6190": {
    "description": "Provider Get Volume Replication Error",
    "message": "Failed to get volume replication details from provider",
    "retriable": false,
    "http_code": 500
  },
  "6191": {
    "description": "Provider Break Volume Replication Error",
    "message": "Failed to break volume replication",
    "retriable": false,
    "http_code": 500
  },
  "6192": {
    "description": "Provider Abort Volume Replication Error",
    "message": "Failed to abort volume replication",
    "retriable": false,
    "http_code": 500
  },
  "6193": {
    "description": "Google Proxy Internal Reverse Replication",
    "message": "Failed to reverse replication on ontap",
    "retriable": false,
    "http_code": 500
  },
  "6194": {
    "description": "Failed to update volume replication attributes on src",
    "message": "Failed to update volume replication details",
    "retriable": false,
    "http_code": 500
  },
  "6195": {
    "description": "Google Proxy Internal Update Volume Replication",
    "message": "Failed to update volume replication",
    "retriable": false,
    "http_code": 500
    },
  "6196": {
    "description": "Google Proxy Internal Delete Volume Replication Error",
    "message": "Error deleting volume replication",
    "retriable": false,
    "http_code": 500
  },
  "6197": {
    "description": "Google Proxy Internal Stop Volume Replication Error",
    "message": "Error stopping volume replication",
    "retriable": false,
    "http_code": 500
  },
  "6198": {
    "description": "Google Proxy Internal Release Volume Replication Error",
    "message": "Error releasing volume replication",
    "retriable": false,
    "http_code": 500
  },
  "6199": {
    "description": "Google Proxy Delete Volume Error",
    "message": "Error deleting volume",
    "retriable": false,
    "http_code": 500
  },
  "6200": {
    "description": "Google Proxy Internal Delete Volume Snapmirror Snapshot Destination Error",
    "message": "Error deleting volume snapmirror snapshot on destination",
    "retriable": false,
    "http_code": 500
  },
  "6201": {
    "description": "Google Proxy Internal Delete Volume Snapmirror Snapshot Source Error",
    "message": "Error deleting volume snapmirror snapshot on source",
    "retriable": false,
    "http_code": 500
  },
  "6202": {
    "description": "Google Proxy Internal Get Multiple Replications For Delete Error",
    "message": "Error getting multiple replications for delete",
    "retriable": false,
    "http_code": 500
  },
  "6203": {
    "description": "Google Proxy Get Multiple Replications Error",
    "message": "Failed to get replication",
    "retriable": false,
    "http_code": 500
  },
  "6204": {
    "description": "Google Proxy Describe Pool Error",
    "message": "Failed to describe pool",
    "retriable": false,
    "http_code": 500
  },
  "6205": {
    "description": "Google Proxy Internal Update Volume Error",
    "message": "Failed to update volume internal",
    "retriable": false,
    "http_code": 500
  },
  "6206": {
    "description": "Provider Delete Volume Replication Error",
    "message": "Failed to Delete volume replication",
    "retriable": false,
    "http_code": 500
  },
  "6207": {
    "description": "Delete Volume Error",
    "message": "Failed to delete volume",
    "retriable": false,
    "http_code": 500
  },
  "6208": {
    "description": "Error returned from internal create replication",
    "message": "Internal error while creating replication",
    "retriable": false,
    "http_code": 500
  },
  "6209": {
    "description": "Describe Destination Volume Error",
    "message": "Failed to describe destination volume",
    "retriable": false,
    "http_code": 500
  },
  "6210": {
    "description": "Failed to cleanup volume replication after reverse",
    "message": "Failed to cleanup volume replication after reverse",
    "retriable": false,
    "http_code": 500
  },
  "6211": {
    "description": "VSA Cluster Operation Error",
    "message": "VSA cluster operation failed",
    "retriable": false,
    "http_code": 400
  },
  "6212": {
    "description": "List Pools for Account Error",
    "message": "Failed to list Pools for Account",
    "retriable": false,
    "http_code": 400
  },
  "6213": {
    "description": "Update Account state Error",
    "message": "Failed to update state for Account",
    "retriable": false,
    "http_code": 400
  },
  "6214": {
    "description": "Autotiering is disabled in Destination Pool",
    "message": "Failed to create destination volume since destination pool has autotiering disabled",
    "retriable": false,
    "http_code": 400
  },
  "6215": {
    "description": "Destination Volume Cooling days out of limits",
    "message": "Failed to create destination volume since cooling days is out of limits. It should be between 2 and 183 days",
    "retriable": false,
    "http_code": 400
  },
  "6216": {
    "description": "Hydrate Volume Replication Create Error",
    "message": "Failed to hydrate volume Replication creation",
    "retriable": false,
    "http_code": 500
  },
  "6217": {
    "description": "Replication is in transferring state, cannot stop replication",
    "message": "Replication is in transferring state, cannot stop replication",
    "retriable": false,
    "http_code": 400
  },
  "6218": {
    "description": "Failed to Delete volume replication",
    "message": "Failed to Delete volume replication",
    "retriable": false,
    "http_code": 400
  },
  "6219": {
    "description": "Failed to update volume replication state on dst",
    "message": "Failed to update volume replication state on",
    "retriable": false,
    "http_code": 500
  },
  "6220": {
    "description": "CRR cannot be created between normal and large capacity pools",
    "message": "CRR cannot be created between normal and large capacity pools",
    "retriable": false,
    "http_code": 400
  },
  "6221": {
    "description": "SVM peering cannot be deleted",
    "message": "Relationship is in use by SnapMirror in peer cluster, Delete the replication first on on-prem cluster and then try again",
    "retriable": false,
    "http_code": 400
  },
  "6222": {
    "description": "Validate Source Storage Pool State Error",
    "message": "Source pool is in unhealthy state, Please try after some time",
    "retriable": false,
    "http_code": 400
  },
  "6223": {
    "description": "Validate Source Storage Pool State Degraded Error",
    "message": "Source pool is in degraded state, please try after some time",
    "retriable": false,
    "http_code": 409
  },
  "6224": {
    "description": "Validate Destination Storage Pool State Degraded Error",
    "message": "Destination pool is in degraded state, please try after some time",
    "retriable": false,
    "http_code": 409
  },
  "8001": {
    "description": "Kms key rotation failure",
    "message": "Error rotating kms key",
    "retriable": true,
    "http_code": 500
  },
  "8002": {
    "description": "Service Account not found for kms configuration",
    "message": "Error rotating kms key - Cannot find service account for kms configuration",
    "retriable": false,
    "http_code": 500
  },
  "8003": {
    "description": "Error while deleting kms configuration in SDE",
    "message": "Internal error while deleting kms configuration",
    "retriable": false,
    "http_code": 500
  },
  "8004": {
    "description": "Error while describing kms configuration in SDE",
    "message": "Internal error while describing kms configuration",
    "retriable": false,
    "http_code": 500
  },
  "8005": {
    "description": "Error while getting service account for kms configuration",
    "message": "Error while creating kms service account key",
    "retriable": false,
    "http_code": 500
  },
  "8006": {
    "description": "Error while decrypting kms service account password",
    "message": "Error while creating kms service account key",
    "retriable": false,
    "http_code": 500
  },
  "8007": {
    "description": "Error while synchronizing kms service account keys",
    "message": "Error while creating kms service account key",
    "retriable": false,
    "http_code": 500
  },
  "8008": {
    "description": "Zone Machine Type Validation Failed",
    "message": "Resource unavailable. Please contact support.",
    "retriable": false,
    "http_code": 507
  },
  "8009": {
    "description": "CMEK precondition failure - KMS key disabled or destroyed",
    "message": "FAILED_PRECONDITION: KMS key is disabled or destroyed",
    "retriable": false,
    "http_code": 412
  },
  "8010": {
    "description": "CMEK precondition failure - Cloud EKM key unreachable",
    "message": "FAILED_PRECONDITION: KMS key in Cloud EKM is unreachable. Retry later or contact your external key manager",
    "retriable": true,
    "http_code": 412
  },
  "10001": {
    "description": "Error creating FlexCache volume",
    "message": "Error creating FlexCache volume",
    "retriable": false,
    "http_code": 400
  },
  "10002": {
    "description": "Error unmounting FlexCache volume",
    "message": "Error unmounting FlexCache volume",
    "retriable": false,
    "http_code": 400
  },
  "10003": {
    "description": "Error deleting FlexCache volume",
    "message": "Error deleting FlexCache volume",
    "retriable": false,
    "http_code": 400
  },
  "10004": {
    "description": "Error updating FlexCache volume",
    "message": "Error updating FlexCache volume",
    "retriable": false,
    "http_code": 400
  },
  "10005": {
    "description": "Error hydrating FlexCache volume",
    "message": "Error hydrating FlexCache volume",
    "retriable": false,
    "http_code": 400
  },
  "10006": {
    "description": "Origin volume not encrypted",
    "message": "Error creating FlexCache volume - Origin volume is not encrypted",
    "retriable": false,
    "http_code": 409
  },
  "11000": {
    "description": "Error during cluster peering",
    "message": "Error during cluster peering",
    "retriable": false,
    "http_code": 400
  },
  "11001": {
    "description": "Cluster peering expired",
    "message": "Cluster peering expired",
    "retriable": false,
    "http_code": 408
  },
  "11002": {
    "description": "Error during SVM peering",
    "message": "Error during SVM peering",
    "retriable": false,
    "http_code": 400
  },
  "11003": {
    "description": "SVM peering expired",
    "message": "SVM peering expired",
    "retriable": false,
    "http_code": 408
  },
  "11004": {
    "description": "Error deleting cluster peer",
    "message": "Error deleting cluster peer",
    "retriable": false,
    "http_code": 400
  },
  "11005": {
    "description": "Error deleting SVM peer",
    "message": "Error deleting SVM peer",
    "retriable": false,
    "http_code": 400
  },
  "11006": {
    "description": "Cluster peering job failed",
    "message": "Cluster peering job failed",
    "retriable": false,
    "http_code": 408
  },
  "11007": {
    "description": "Internal peering job failed",
    "message": "Internal peering job failed",
    "retriable": false,
    "http_code": 408
  },
  "11008": {
    "description": "Cluster peer not found",
    "message": "Cluster peer not found",
    "retriable": false,
    "http_code": 404
  },
  "11009": {
    "description": "Error creating cluster peer - CVI source cluster unreachable",
    "message": "Source cluster is unreachable. Please verify that the peer address is correct and try again",
    "retriable": false,
    "http_code": 400
  },
  "11010": {
    "description": "Cluster peer is not available",
    "message": "Cluster peer is not available",
    "retriable": false,
    "http_code": 400
  },
  "11011": {
    "description": "SVM peer is not available",
    "message": "SVM peer is not available",
    "retriable": false,
    "http_code": 400
  },
  "12001": {
    "description": "Immutable backup validation failed due to backup policy update",
    "message": "Error while creating immutable backup when backup policy is in updating state",
    "retriable": true,
    "http_code": 400
  },
  "12002": {
    "description": "Immutable backup validation failed due to backup vault update",
    "message": "Immutable backup vault is being updated",
    "retriable": true,
    "http_code": 400
  },
  "12003": {
    "description": "Google Proxy Internal Create Quota Rule Error",
    "message": "Failed to create quota rule on destination via VCP internal API",
    "retriable": false,
    "http_code": 500
  },
  "12004": {
    "description": "Files missing in backup after transfer completion",
    "message": "Transfer completed for %d file(s), but the following file(s) are not present in the backup: %s",
    "retriable": false,
    "http_code": 400
  },
  "12005": {
    "description": "No Files Found in Backup for Specified File List",
    "message": "No files found in backup for the specified file list",
    "retriable": false,
    "http_code": 400
  },
  "12006": {
    "description": "Matching quota rule not found on destination",
    "message": "Matching quota rule not found on destination",
    "retriable": false,
    "http_code": 404
  },
  "12007": {
    "description": "Quota rule not found",
    "message": "Quota rule not found",
    "retriable": false,
    "http_code": 404
  },
  "12008": {
    "description": "Quota rule bad request error",
    "message": "Bad request error while processing quota rule operation",
    "retriable": false,
    "http_code": 400
  },
  "12009": {
    "description": "Quota rule unauthorized error",
    "message": "Unauthorized error while processing quota rule operation",
    "retriable": false,
    "http_code": 401
  },
  "12010": {
    "description": "Quota rule forbidden error",
    "message": "Forbidden error while processing quota rule operation",
    "retriable": false,
    "http_code": 403
  },
  "12011": {
    "description": "Quota rule conflict error",
    "message": "Conflict error while processing quota rule operation",
    "retriable": false,
    "http_code": 409
  },
  "12012": {
    "description": "Quota rule too many requests error",
    "message": "Too many requests error while processing quota rule operation",
    "retriable": true,
    "http_code": 429
  },
  "12013": {
    "description": "Quota rule internal server error",
    "message": "Internal server error while processing quota rule operation",
    "retriable": true,
    "http_code": 500
  },
  "12014": {
    "description": "Resume replication quota rule failure",
    "message": "Operation was successful but quota rule sync between source and destination failed",
    "retriable": false,
    "http_code": 200
  }
}